tests/__init__.py
tests/conftest.py
tests/test_citationFileFormat.py
tests/test_flowControl.py
tests/test_github.py
tests/test_pypa.py
tests/test_pypi.py
tests/test_variables.py
updateCitation/__init__.py
updateCitation/citationFileFormat.py
updateCitation/flowControl.py
updateCitation/github.py
updateCitation/py.typed
updateCitation/pypa.py
updateCitation/pypi.py
updateCitation/pyprojectDOTtoml.py
updateCitation/variables.py
updatecitation-0.0.11.dist-info/licenses/LICENSE
updatecitation-0.0.11.dist-info/METADATA
updatecitation-0.0.11.dist-info/WHEEL
updatecitation-0.0.11.dist-info/top_level.txt
updatecitation-0.0.11.dist-info/RECORD
