Metadata-Version: 2.4
Name: updateCitation
Version: 0.0.11
Summary: Automatically update citation files (CITATION.cff) in a GitHub repository from `pyproject.toml`, GitHub releases, and PyPI releases.
Author-email: Hunter Hogan <HunterHogan@pm.me>
License: CC-BY-NC-4.0
Project-URL: Donate, https://www.patreon.com/integrated
Project-URL: Homepage, https://github.com/hunterhogan/updateCitation
Project-URL: Repository, https://github.com/hunterhogan/updateCitation.git
Keywords: academic-software,automation,cff,citation,citation-files,doi,github,metadata,publishing,references,research-software,scholarly-communication,software-citation,zenodo
Classifier: Development Status :: 3 - Alpha
Classifier: Environment :: Console
Classifier: Framework :: Pytest
Classifier: Intended Audience :: Developers
Classifier: Intended Audience :: Information Technology
Classifier: Intended Audience :: Science/Research
Classifier: Natural Language :: English
Classifier: Operating System :: OS Independent
Classifier: Programming Language :: Python
Classifier: Programming Language :: Python :: 3
Classifier: Programming Language :: Python :: 3.11
Classifier: Programming Language :: Python :: 3.12
Classifier: Programming Language :: Python :: 3.13
Classifier: Topic :: Scientific/Engineering
Classifier: Topic :: Software Development :: Documentation
Classifier: Topic :: Software Development :: Libraries :: Python Modules
Classifier: Topic :: Text Processing :: Markup
Classifier: Topic :: Utilities
Classifier: Typing :: Typed
Requires-Python: >=3.11
License-File: LICENSE
Requires-Dist: attrs
Requires-Dist: cffconvert
Requires-Dist: packaging
Requires-Dist: pygithub
Requires-Dist: ruamel.yaml
Provides-Extra: development
Requires-Dist: mypy; extra == "development"
Requires-Dist: pyupgrade; extra == "development"
Requires-Dist: setuptools-scm; extra == "development"
Provides-Extra: testing
Requires-Dist: pytest; extra == "testing"
Requires-Dist: pytest-cov; extra == "testing"
Requires-Dist: pytest-xdist; extra == "testing"
Dynamic: license-file
